tom_hermes/__init__.py
tom_hermes/hermes.py
tom_hermes/templates/tom_hermes/query_result.html
tom_hermes-0.1.10.dist-info/LICENSE
tom_hermes-0.1.10.dist-info/METADATA
tom_hermes-0.1.10.dist-info/WHEEL
tom_hermes-0.1.10.dist-info/RECORD
